<annotation>
	<folder>at</folder>
	<filename>at (12).jpg</filename>
	<path>G:\Augmented Final pics\at\at (12).jpg</path>
	<source>
		<database>Unknown</database>
	</source>
	<size>
		<width>770</width>
		<height>660</height>
		<depth>3</depth>
	</size>
	<segmented>0</segmented>
	<object>
		<name>At</name>
		<pose>Unspecified</pose>
		<truncated>0</truncated>
		<difficult>0</difficult>
		<bndbox>
			<xmin>379</xmin>
			<ymin>168</ymin>
			<xmax>536</xmax>
			<ymax>233</ymax>
		</bndbox>
	</object>
</annotation>
