<annotation>
	<folder>builder</folder>
	<filename>builder (4).jpg</filename>
	<path>G:\Augmented Final pics\builder\builder (4).jpg</path>
	<source>
		<database>Unknown</database>
	</source>
	<size>
		<width>770</width>
		<height>660</height>
		<depth>3</depth>
	</size>
	<segmented>0</segmented>
	<object>
		<name>Builder</name>
		<pose>Unspecified</pose>
		<truncated>0</truncated>
		<difficult>0</difficult>
		<bndbox>
			<xmin>380</xmin>
			<ymin>192</ymin>
			<xmax>612</xmax>
			<ymax>411</ymax>
		</bndbox>
	</object>
</annotation>
